semantic_cleaning/__init__.py
semantic_cleaning/_modidx.py
semantic_cleaning/core.py
semantic_cleaning-0.0.4.dist-info/LICENSE
semantic_cleaning-0.0.4.dist-info/METADATA
semantic_cleaning-0.0.4.dist-info/WHEEL
semantic_cleaning-0.0.4.dist-info/entry_points.txt
semantic_cleaning-0.0.4.dist-info/top_level.txt
semantic_cleaning-0.0.4.dist-info/RECORD
