Metadata-Version: 2.1
Name: semantic-cleaning
Version: 0.0.4
Summary: Tools for semantic cleaning of a test dataset
Home-page: https://github.com/yuval6957/semantic-cleaning
Author: Yuval Reina
Author-email: yuval.reina@gmail.com
License: Apache Software License 2.0
Keywords: nbdev jupyter notebook python
Platform: UNKNOWN
Classifier: Development Status :: 4 - Beta
Classifier: Intended Audience :: Developers
Classifier: Natural Language :: English
Classifier: Programming Language :: Python :: 3.7
Classifier: Programming Language :: Python :: 3.8
Classifier: Programming Language :: Python :: 3.9
Classifier: Programming Language :: Python :: 3.10
Classifier: License :: OSI Approved :: Apache Software License
Requires-Python: >=3.7
License-File: LICENSE
Requires-Dist: torch
Requires-Dist: tqdm
Requires-Dist: numpy
Requires-Dist: transformers
Requires-Dist: datasets
Provides-Extra: dev
Requires-Dist: reinautils ; extra == 'dev'
